pykefcontrol/__init__.py
pykefcontrol/kef_connector.py
pykefcontrol-0.8.dist-info/METADATA
pykefcontrol-0.8.dist-info/WHEEL
pykefcontrol-0.8.dist-info/licenses/LICENSE
pykefcontrol-0.8.dist-info/RECORD
