Metadata-Version: 2.4
Name: pykefcontrol
Version: 0.8
Summary: Python library for controling KEF speakers (LS50W2, LSX2, LS60). It supports basic commands for setting the volume, the source, and getting the media playing informations.
License: MIT
License-File: LICENSE
Keywords: Kef,KEF,Speaker,LS50,LS50W2,Wireless II,Wireless 2,LSX,LSX2,LS60,LS60W
Author: Robin Dupont
Author-email: robin.dpnt@gmail.com
Requires-Python: >=3.10,<4.0
Classifier: Development Status :: 4 - Beta
Classifier: Intended Audience :: Developers
Classifier: License :: OSI Approved :: MIT License
Classifier: Programming Language :: Python :: 3
Classifier: Programming Language :: Python :: 3.10
Classifier: Programming Language :: Python :: 3.11
Classifier: Programming Language :: Python :: 3.12
Classifier: Programming Language :: Python :: 3.13
Classifier: Programming Language :: Python :: 3.14
Classifier: Programming Language :: Python :: 3.7
Classifier: Programming Language :: Python :: 3.8
Classifier: Programming Language :: Python :: 3.9
Classifier: Topic :: Home Automation
Requires-Dist: aiohttp (>=3.7.4)
Requires-Dist: requests (>=2.26.0)
Project-URL: Homepage, https://github.com/rodupont/pykefcontrol
Project-URL: Repository, https://github.com/rodupont/pykefcontrol
